[
  {
    "model": "app.Physical_Store",
    "pk": 1,
    "fields": {
      "street": "University Drive",
      "city": "Calgary",
      "province": "Alberta",
      "country": "Canada",
      "postal_code": "T2W 8L2",
      "phone": "4035671203",
      "email": "university@university.com",
      "fax_number": "9998887654",
      "store_name": "University Store"
    }
  },
  {
    "model": "app.Physical_Store",
    "pk": 2,
    "fields": {
      "street": "Sait Drive",
      "city": "Calgary",
      "province": "Alberta",
      "country": "Canada",
      "postal_code": "T2X 0W2",
      "phone": "5874579087",
      "email": "edu@edu.com",
      "fax_number": "1234567891",
      "store_name": "Student Tech Needs"
    }
  }
]